pubsub_emulator_messaging_setup/__init__.py
pubsub_emulator_messaging_setup/cli.py
pubsub_emulator_messaging_setup/core.py
pubsub_emulator_messaging_setup/pubsub.py
pubsub_emulator_messaging_setup/types.py
pubsub_emulator_messaging_setup/utils.py
pubsub_emulator_messaging_setup-0.1.0.dist-info/entry_points.txt
pubsub_emulator_messaging_setup-0.1.0.dist-info/LICENSE
pubsub_emulator_messaging_setup-0.1.0.dist-info/WHEEL
pubsub_emulator_messaging_setup-0.1.0.dist-info/METADATA
pubsub_emulator_messaging_setup-0.1.0.dist-info/RECORD
