Metadata-Version: 2.1
Name: pubsub-emulator-messaging-setup
Version: 0.1.0
Summary: CLI tool to setup topics and subscriptions on a PubSub emulator from a definition in a YAML file
Home-page: https://github.com/expobrain/pubsub-emulator-messaging-setup
License: MIT
Author: Daniele Esposti
Author-email: daniele.esposti@gmail.com
Requires-Python: >=3.7,<3.12
Classifier: License :: OSI Approved :: MIT License
Classifier: Programming Language :: Python :: 3
Classifier: Programming Language :: Python :: 3.7
Classifier: Programming Language :: Python :: 3.8
Classifier: Programming Language :: Python :: 3.9
Classifier: Programming Language :: Python :: 3.10
Classifier: Programming Language :: Python :: 3.11
Requires-Dist: PyYAML (>=6.0)
Requires-Dist: click (>=8.1)
Requires-Dist: google-api-core (>=2.10)
Requires-Dist: google-auth (>=2.13)
Requires-Dist: google-cloud-pubsub (>=2.13)
Requires-Dist: grpcio (>=1.50)
Requires-Dist: loguru (>=0.6)
Requires-Dist: pydantic (>=1.10)
Project-URL: Repository, https://github.com/expobrain/pubsub-emulator-messaging-setup
